README.txt
setup.cfg
setup.py
lcb/__init__.py
lcb.egg-info/PKG-INFO
lcb.egg-info/SOURCES.txt
lcb.egg-info/dependency_links.txt
lcb.egg-info/top_level.txt