Metadata-Version: 1.0
Name: lcb
Version: 1.4
Summary: An awesome package that does something
Home-page: https://github.com/ljelschen/lcb
Author: lejlschen
Author-email: mail@lars-jelschen.de
License: LICENSE.txt
Platform: UNKNOWN
